etupem/__init__.py
etupem/__main__.py
etupem/exec.py
etupem/ja.py
etupem-0.4.4.dist-info/LICENSE
etupem-0.4.4.dist-info/METADATA
etupem-0.4.4.dist-info/WHEEL
etupem-0.4.4.dist-info/entry_points.txt
etupem-0.4.4.dist-info/top_level.txt
etupem-0.4.4.dist-info/RECORD
