Metadata-Version: 2.1
Name: etupem
Version: 0.4.4
Summary: make Easy To Understand Python Error Message for those who are not good at English.
Home-page: https://github.com/nodai2hITC/etupem/
Author: nodai2hITC
Author-email: nodai2h.itc@gmail.com
License: MIT
Platform: UNKNOWN
Classifier: Programming Language :: Python :: 3
Classifier: License :: OSI Approved :: MIT License
Classifier: Operating System :: OS Independent
Requires-Python: >=3.8
License-File: LICENSE
Requires-Dist: colorama (>=0.4.6)
